gcoinbuild/__init__.py
gcoinbuild-0.0.34.dist-info/LICENSE
gcoinbuild-0.0.34.dist-info/METADATA
gcoinbuild-0.0.34.dist-info/WHEEL
gcoinbuild-0.0.34.dist-info/top_level.txt
gcoinbuild-0.0.34.dist-info/RECORD
