Metadata-Version: 2.1
Name: gcoinbuild
Version: 0.0.34
Summary: Official GCoin Library
Home-page: UNKNOWN
Author: Yek
Author-email: gwojtysiak34@gmail.com
License: UNKNOWN
Platform: UNKNOWN
Classifier: Programming Language :: Python :: 3
Classifier: License :: OSI Approved :: MIT License
Classifier: Operating System :: OS Independent
Requires-Python: >=3.6
